Workbook

Sheet Yearly Summary
A1: Year | B1: Capex | C1: Opex | D1: Revenue | E1: Cash Flow | F1: Discounted CF
A2: 0 | B2: =$B$10*$B$13 -> -100000 | E2: =D2+C2+B2 -> -100000 | F2: =E2/(1+$B$11)^A2 -> -100000 | H2: KEY SALES ASSUMPTIONS
A3: 1 | B3: =3*$B$10*$B$13 -> -300000 | C3: ='Monthly Opex'!N6*$B$13 -> -137350 | D3: ='Monthly Sales'!N7 -> 233451.77 | E3: =D3+C3+B3 -> -203898.23 | F3: =E3/(1+$B$11)^A3 -> -188794.65 | H3: Market Entry / Pipeline | I3: ='Monthly Sales'!B10 -> 5000
A4: 2 | C4: ='Monthly Opex'!N20*$B$13 -> -156683 | D4: ='Monthly Sales'!N20 -> 299951.63 | E4: =D4+C4+B4 -> 143268.63 | F4: =E4/(1+$B$11)^A4 -> 122829.76 | H4: Market Entry Ramp Up (mo) | I4: ='Monthly Opex'!B12 -> 4
A5: 3 | C5: =C4 -> -156683 | D5: ='Monthly Sales'!N29 -> 300437.83 | E5: =D5+C5+B5 -> 143754.83 | F5: =E5/(1+$B$11)^A5 -> 114117.22 | H5: Monthly Escalation | I5: ='Monthly Sales'!B11 -> 0.02
A6: 4 | C6: =C5 -> -156683 | D6: =D5 -> 300437.83 | E6: =D6+C6+B6 -> 143754.83 | F6: =E6/(1+$B$11)^A6 -> 105664.09 | H6: Monthly Sales Cap per Market | I6: ='Monthly Sales'!M3 -> 6216.8715
A7: 5 | C7: =C6 -> -156683 | D7: =D6 -> 300437.83 | E7: =D7+C7+B7 -> 143754.83 | F7: =E7/(1+$B$11)^A7 -> 97837.125 | H7: Total Sales over 5 years | I7: =D8 -> 1434716.9
B8: =sum(B2:B7) -> -400000 | C8: =sum(C2:C7) -> -764082 | D8: =sum(D2:D7) -> 1434716.9 | E8: =sum(E2:E7) -> 270634.9 | F8: =SUM(F2:F7) -> 151653.54
A9: Assumptions | D9: Results | H9: BUDGET REQUESTS
A10: Capex Per DC | B10: 100000 | D10: NPV | E10: {=npv(B11,E3:E7)+E2} -> 151653.54 | H10: Capital Expenses in 2026 | I10: =B8*B13 -> 400000
A11: Discount Rate | B11: 0.08 | D11: IRR | E11: =irr(E2:E7,0.03) -> 0.26477174 | H11: Operating Expenses over 5 years | I11: =C8*B13 -> 764082
A13: Negative costs | B13: -1 | H13: USES OF BUDGET
H14: Network Equipment | I14: =B8*B13 -> 400000
H15: Colocation | I15: ='Monthly Opex'!N3+'Monthly Opex'!N17*4 -> 128700
H16: Power | I16: ='Monthly Opex'!N4+'Monthly Opex'!N18*4 -> 157248
H17: Transit | I17: ='Monthly Opex'!N5+'Monthly Opex'!N19*4 -> 468000
J29: KEY METRICS
J30: NPV @ 8% | K30: =E10 -> 151653.54
J31: IRR | K31: =E11 -> 0.26477174
J32: VAR (95th %ile) | K32: 50702
B35: Today | C35: Next Year | D35: Discount % | E35: Which do you choose?
B36: 100 | C36: 100 | D36: 0 | E36: Today
B37: 100 | C37: 105 | D37: 0.05 | E37: Either
B38: 100 | C38: 105 | D38: 0.08 | E38: Today

Sheet Monthly Sales
N1: Year end Total
A2: Month | B2: 1 | C2: 2 | D2: 3 | E2: 4 | F2: 5 | G2: 6 | H2: 7 | I2: 8 | J2: 9 | K2: 10 | L2: 11 | M2: 12 | N2: 2026
A3: New York | B3: =$B$10 -> 5000 | C3: =B3*(1+$B$11) -> 5100 | D3: =C3*(1+$B$11) -> 5202 | E3: =D3*(1+$B$11) -> 5306.04 | F3: =E3*(1+$B$11) -> 5412.1608 | G3: =F3*(1+$B$11) -> 5520.404 | H3: =G3*(1+$B$11) -> 5630.8121 | I3: =H3*(1+$B$11) -> 5743.4283 | J3: =I3*(1+$B$11) -> 5858.2969 | ... M3: =L3*(1+$B$11) -> 6216.8715 | N3: =sum(B3:M3) -> 67060.449
A4: San Francisco | C4: =$B$10 -> 5000 | D4: =C4*(1+$B$11) -> 5100 | E4: =D4*(1+$B$11) -> 5202 | F4: =E4*(1+$B$11) -> 5306.04 | G4: =F4*(1+$B$11) -> 5412.1608 | H4: =G4*(1+$B$11) -> 5520.404 | I4: =H4*(1+$B$11) -> 5630.8121 | J4: =I4*(1+$B$11) -> 5743.4283 | K4: =J4*(1+$B$11) -> 5858.2969 | ... M4: =L4*(1+$B$11) -> 6094.9721 | N4: =sum(B4:M4) -> 60843.577
A5: Dallas | D5: =$B$10 -> 5000 | E5: =D5*(1+$B$11) -> 5100 | F5: =E5*(1+$B$11) -> 5202 | G5: =F5*(1+$B$11) -> 5306.04 | H5: =G5*(1+$B$11) -> 5412.1608 | I5: =H5*(1+$B$11) -> 5520.404 | J5: =I5*(1+$B$11) -> 5630.8121 | K5: =J5*(1+$B$11) -> 5743.4283 | L5: =K5*(1+$B$11) -> 5858.2969 | M5: =L5*(1+$B$11) -> 5975.4628 | N5: =sum(B5:M5) -> 54748.605
A6: Chicago | E6: =$B$10 -> 5000 | F6: =E6*(1+$B$11) -> 5100 | G6: =F6*(1+$B$11) -> 5202 | H6: =G6*(1+$B$11) -> 5306.04 | I6: =H6*(1+$B$11) -> 5412.1608 | J6: =I6*(1+$B$11) -> 5520.404 | K6: =J6*(1+$B$11) -> 5630.8121 | L6: =K6*(1+$B$11) -> 5743.4283 | M6: =L6*(1+$B$11) -> 5858.2969 | N6: =sum(B6:M6) -> 48773.142
N7: =SUM(N2:N6) -> 233451.77
A9: Assumptions
A10: Market Entry | B10: 5000
A11: Growth Rate/mo | B11: 0.02
N14: Year end Total
A15: Month | B15: 1 | C15: 2 | D15: 3 | E15: 4 | F15: 5 | G15: 6 | H15: 7 | I15: 8 | J15: 9 | K15: 10 | L15: 11 | M15: 12 | N15: 2027
A16: New York | B16: =$M$3 -> 6216.8715 | C16: =$M$3 -> 6216.8715 | D16: =$M$3 -> 6216.8715 | E16: =$M$3 -> 6216.8715 | F16: =$M$3 -> 6216.8715 | G16: =$M$3 -> 6216.8715 | H16: =$M$3 -> 6216.8715 | I16: =$M$3 -> 6216.8715 | ... M16: =$M$3 -> 6216.8715 | N16: =sum(B16:M16) -> 74602.458
A17: San Francisco | B17: =if(GTE($M4,$M$3),$M$3,$M4*(1+$B$11)) -> 6216.8715 | C17: =if(GTE(B17,$M$3),$M$3,B17*(1+$B$11)) -> 6216.8715 | D17: =if(GTE(C17,$M$3),$M$3,C17*(1+$B$11)) -> 6216.8715 | E17: =if(GTE(D17,$M$3),$M$3,D17*(1+$B$11)) -> 6216.8715 | F17: =if(GTE(E17,$M$3),$M$3,E17*(1+$B$11)) -> 6216.8715 | G17: =if(GTE(F17,$M$3),$M$3,F17*(1+$B$11)) -> 6216.8715 | H17: =if(GTE(G17,$M$3),$M$3,G17*(1+$B$11)) -> 6216.8715 | I17: =if(GTE(H17,$M$3),$M$3,H17*(1+$B$11)) -> 6216.8715 | J17: =if(GTE(I17,$M$3),$M$3,I17*(1+$B$11)) -> 6216.8715 | ... M17: =if(GTE(L17,$M$3),$M$3,L17*(1+$B$11)) -> 6216.8715 | N17: =sum(B17:M17) -> 74602.458
A18: Dallas | B18: =if(GTE($M5,$M$3),$M$3,$M5*(1+$B$11)) -> 6094.9721 | C18: =if(GTE(B18,$M$3),$M$3,B18*(1+$B$11)) -> 6216.8715 | D18: =if(GTE(C18,$M$3),$M$3,C18*(1+$B$11)) -> 6216.8715 | E18: =if(GTE(D18,$M$3),$M$3,D18*(1+$B$11)) -> 6216.8715 | F18: =if(GTE(E18,$M$3),$M$3,E18*(1+$B$11)) -> 6216.8715 | G18: =if(GTE(F18,$M$3),$M$3,F18*(1+$B$11)) -> 6216.8715 | H18: =if(GTE(G18,$M$3),$M$3,G18*(1+$B$11)) -> 6216.8715 | I18: =if(GTE(H18,$M$3),$M$3,H18*(1+$B$11)) -> 6216.8715 | J18: =if(GTE(I18,$M$3),$M$3,I18*(1+$B$11)) -> 6216.8715 | ... M18: =if(GTE(L18,$M$3),$M$3,L18*(1+$B$11)) -> 6216.8715 | N18: =sum(B18:M18) -> 74480.559
A19: Chicago | B19: =if(GTE($M6,$M$3),$M$3,$M6*(1+$B$11)) -> 5975.4628 | C19: =if(GTE(B19,$M$3),$M$3,B19*(1+$B$11)) -> 6094.9721 | D19: =if(GTE(C19,$M$3),$M$3,C19*(1+$B$11)) -> 6216.8715 | E19: =if(GTE(D19,$M$3),$M$3,D19*(1+$B$11)) -> 6216.8715 | F19: =if(GTE(E19,$M$3),$M$3,E19*(1+$B$11)) -> 6216.8715 | G19: =if(GTE(F19,$M$3),$M$3,F19*(1+$B$11)) -> 6216.8715 | H19: =if(GTE(G19,$M$3),$M$3,G19*(1+$B$11)) -> 6216.8715 | I19: =if(GTE(H19,$M$3),$M$3,H19*(1+$B$11)) -> 6216.8715 | J19: =if(GTE(I19,$M$3),$M$3,I19*(1+$B$11)) -> 6216.8715 | ... M19: =if(GTE(L19,$M$3),$M$3,L19*(1+$B$11)) -> 6216.8715 | N19: =sum(B19:M19) -> 74239.15
N20: =SUM(N15:N19) -> 299951.63
N23: Year end Total
A24: Month | B24: 1 | C24: 2 | D24: 3 | E24: 4 | F24: 5 | G24: 6 | H24: 7 | I24: 8 | J24: 9 | K24: 10 | L24: 11 | M24: 12 | N24: 2028
A25: New York | B25: =$M$3 -> 6216.8715 | C25: =$M$3 -> 6216.8715 | D25: =$M$3 -> 6216.8715 | E25: =$M$3 -> 6216.8715 | F25: =$M$3 -> 6216.8715 | G25: =$M$3 -> 6216.8715 | H25: =$M$3 -> 6216.8715 | I25: =$M$3 -> 6216.8715 | ... M25: =$M$3 -> 6216.8715 | N25: =sum(B25:M25) -> 74602.458
A26: San Francisco | B26: =$M$3 -> 6216.8715 | C26: =$M$3 -> 6216.8715 | D26: =$M$3 -> 6216.8715 | E26: =$M$3 -> 6216.8715 | F26: =$M$3 -> 6216.8715 | G26: =$M$3 -> 6216.8715 | H26: =$M$3 -> 6216.8715 | I26: =$M$3 -> 6216.8715 | ... M26: =$M$3 -> 6216.8715 | N26: =sum(B26:M26) -> 74602.458
A27: Dallas | B27: =$M$3 -> 6216.8715 | C27: =$M$3 -> 6216.8715 | D27: =$M$3 -> 6216.8715 | E27: =$M$3 -> 6216.8715 | F27: =$M$3 -> 6216.8715 | G27: =$M$3 -> 6216.8715 | H27: =$M$3 -> 6216.8715 | I27: =$M$3 -> 6216.8715 | ... M27: =$M$3 -> 6216.8715 | N27: =sum(B27:M27) -> 74602.458
A28: Chicago | B28: =$M$3 -> 6216.8715 | C28: =$M$3 -> 6216.8715 | D28: =$M$3 -> 6216.8715 | E28: =$M$3 -> 6216.8715 | F28: =$M$3 -> 6216.8715 | G28: =$M$3 -> 6216.8715 | H28: =$M$3 -> 6216.8715 | I28: =$M$3 -> 6216.8715 | ... M28: =$M$3 -> 6216.8715 | N28: =sum(B28:M28) -> 74602.458
N29: =SUM(N24:N28) -> 300437.83

Sheet Monthly Opex
N1: Year end Total
A2: Month | B2: 1 | C2: 2 | D2: 3 | E2: 4 | F2: 5 | G2: 6 | H2: 7 | I2: 8 | J2: 9 | K2: 10 | L2: 11 | M2: 12 | N2: 2026
A3: Colocation | B3: =if(LT(B$2,$B$12),$B9*B$2,$B9*$B$12) -> 550 | C3: =if(LT(C$2,$B$12),$B9*C$2,$B9*$B$12) -> 1100 | D3: =if(LT(D$2,$B$12),$B9*D$2,$B9*$B$12) -> 1650 | E3: =if(LT(E$2,$B$12),$B9*E$2,$B9*$B$12) -> 2200 | F3: =if(LT(F$2,$B$12),$B9*F$2,$B9*$B$12) -> 2200 | G3: =if(LT(G$2,$B$12),$B9*G$2,$B9*$B$12) -> 2200 | H3: =if(LT(H$2,$B$12),$B9*H$2,$B9*$B$12) -> 2200 | I3: =if(LT(I$2,$B$12),$B9*I$2,$B9*$B$12) -> 2200 | ... M3: =if(LT(M$2,$B$12),$B9*M$2,$B9*$B$12) -> 2200 | N3: =SUM(B3:M3) -> 23100
A4: Power | B4: =if(LT(B$2,$B$12),$B10*B$2,$B10*$B$12) -> 672 | C4: =if(LT(C$2,$B$12),$B10*C$2,$B10*$B$12) -> 1344 | D4: =if(LT(D$2,$B$12),$B10*D$2,$B10*$B$12) -> 2016 | E4: =if(LT(E$2,$B$12),$B10*E$2,$B10*$B$12) -> 2688 | F4: =if(LT(F$2,$B$12),$B10*F$2,$B10*$B$12) -> 2688 | G4: =if(LT(G$2,$B$12),$B10*G$2,$B10*$B$12) -> 2688 | H4: =if(LT(H$2,$B$12),$B10*H$2,$B10*$B$12) -> 2688 | I4: =if(LT(I$2,$B$12),$B10*I$2,$B10*$B$12) -> 2688 | ... M4: =if(LT(M$2,$B$12),$B10*M$2,$B10*$B$12) -> 2688 | N4: =SUM(B4:M4) -> 28224
A5: Transit | B5: =if(LT(B$2,$B$12),$B11*B$2,$B11*$B$12) -> 2000 | C5: =if(LT(C$2,$B$12),$B11*C$2,$B11*$B$12) -> 4000 | D5: =if(LT(D$2,$B$12),$B11*D$2,$B11*$B$12) -> 6000 | E5: =if(LT(E$2,$B$12),$B11*E$2,$B11*$B$12) -> 8000 | F5: =if(LT(F$2,$B$12),$B11*F$2,$B11*$B$12) -> 8000 | G5: =if(LT(G$2,$B$12),$B11*G$2,$B11*$B$12) -> 8000 | H5: =if(LT(H$2,$B$12),$B11*H$2,$B11*$B$12) -> 8000 | I5: =if(LT(I$2,$B$12),$B11*I$2,$B11*$B$12) -> 8000 | ... M5: =if(LT(M$2,$B$12),$B11*M$2,$B11*$B$12) -> 8000 | N5: =SUM(B5:M5) -> 84000
N6: =SUM(N2:N5) -> 137350
A8: Assumptions
A9: Colo per rack | B9: 550
A10: Power per rack | B10: 672
A11: Transit per DC | B11: 2000
A12: Ramp up months | B12: 4
N15: Year end Total
A16: Month | B16: 1 | C16: 2 | D16: 3 | E16: 4 | F16: 5 | G16: 6 | H16: 7 | I16: 8 | J16: 9 | K16: 10 | L16: 11 | M16: 12 | N16: 2027
A17: Colocation | B17: =M3 -> 2200 | C17: =B17 -> 2200 | D17: =C17 -> 2200 | E17: =D17 -> 2200 | F17: =E17 -> 2200 | G17: =F17 -> 2200 | H17: =G17 -> 2200 | I17: =H17 -> 2200 | J17: =I17 -> 2200 | ... M17: =L17 -> 2200 | N17: =SUM(B17:M17) -> 26400
A18: Power | B18: =M4 -> 2688 | C18: =B18 -> 2688 | D18: =C18 -> 2688 | E18: =D18 -> 2688 | F18: =E18 -> 2688 | G18: =F18 -> 2688 | H18: =G18 -> 2688 | I18: =H18 -> 2688 | J18: =I18 -> 2688 | ... M18: =L18 -> 2688 | N18: =SUM(B18:M18) -> 32256
A19: Transit | B19: =M5 -> 8000 | C19: =B19 -> 8000 | D19: =C19 -> 8000 | E19: =D19 -> 8000 | F19: =E19 -> 8000 | G19: =F19 -> 8000 | H19: =G19 -> 8000 | I19: =H19 -> 8000 | J19: =I19 -> 8000 | ... M19: =L19 -> 8000 | N19: =SUM(B19:M19) -> 96000
N20: =SUM(N16:N19) -> 156683

Sheet Tornado Inputs
B1: CF, 𝛥 Capex | E1: CF, 𝛥 Opex | H1: CF, 𝛥 Revenue
A2: Year | B2: Nominal | C2: Low | D2: High | E2: Nominal | F2: Low | G2: High | H2: Nominal | I2: Low | J2: High
A3: 0 | B3: =$B15+$E15+$H15 -> -100000 | C3: =$C15+$E15+$H15 -> -50000 | D3: =$D15+$E15+$H15 -> -150000 | E3: =$B15+$E15+$H15 -> -100000 | F3: =$B15+$F15+$H15 -> -100000 | G3: =$B15+$G15+$H15 -> -100000 | H3: =$B15+$E15+$H15 -> -100000 | I3: =$B15+$E15+$I15 -> -100000 | J3: =$B15+$E15+$J15 -> -100000
A4: 1 | B4: =$B16+$E16+$H16 -> -203898.23 | C4: =$C16+$E16+$H16 -> -53898.227 | D4: =$D16+$E16+$H16 -> -353898.23 | E4: =$B16+$E16+$H16 -> -203898.23 | F4: =$B16+$F16+$H16 -> -135223.23 | G4: =$B16+$G16+$H16 -> -272573.23 | H4: =$B16+$E16+$H16 -> -203898.23 | I4: =$B16+$E16+$I16 -> -320624.11 | J4: =$B16+$E16+$J16 -> -87172.341
A5: 2 | B5: =$B17+$E17+$H17 -> 143268.63 | C5: =$C17+$E17+$H17 -> 143268.63 | D5: =$D17+$E17+$H17 -> 143268.63 | E5: =$B17+$E17+$H17 -> 143268.63 | F5: =$B17+$F17+$H17 -> 221610.13 | G5: =$B17+$G17+$H17 -> 64927.126 | H5: =$B17+$E17+$H17 -> 143268.63 | I5: =$B17+$E17+$I17 -> -6707.1868 | J5: =$B17+$E17+$J17 -> 293244.44
A6: 3 | B6: =$B18+$E18+$H18 -> 143754.83 | C6: =$C18+$E18+$H18 -> 143754.83 | D6: =$D18+$E18+$H18 -> 143754.83 | E6: =$B18+$E18+$H18 -> 143754.83 | F6: =$B18+$F18+$H18 -> 222096.33 | G6: =$B18+$G18+$H18 -> 65413.334 | H6: =$B18+$E18+$H18 -> 143754.83 | I6: =$B18+$E18+$I18 -> -6464.083 | J6: =$B18+$E18+$J18 -> 293973.75
A7: 4 | B7: =$B19+$E19+$H19 -> 143754.83 | C7: =$C19+$E19+$H19 -> 143754.83 | D7: =$D19+$E19+$H19 -> 143754.83 | E7: =$B19+$E19+$H19 -> 143754.83 | F7: =$B19+$F19+$H19 -> 222096.33 | G7: =$B19+$G19+$H19 -> 65413.334 | H7: =$B19+$E19+$H19 -> 143754.83 | I7: =$B19+$E19+$I19 -> -6464.083 | J7: =$B19+$E19+$J19 -> 293973.75
A8: 5 | B8: =$B20+$E20+$H20 -> 143754.83 | C8: =$C20+$E20+$H20 -> 143754.83 | D8: =$D20+$E20+$H20 -> 143754.83 | E8: =$B20+$E20+$H20 -> 143754.83 | F8: =$B20+$F20+$H20 -> 222096.33 | G8: =$B20+$G20+$H20 -> 65413.334 | H8: =$B20+$E20+$H20 -> 143754.83 | I8: =$B20+$E20+$I20 -> -6464.083 | J8: =$B20+$E20+$J20 -> 293973.75
A9: NPV | B9: {=B3+npv('Yearly Summary'!$B$11, B4:B8)} -> 151653.54 | C9: {=C3+npv('Yearly Summary'!$B$11, C4:C8)} -> 340542.43 | D9: {=D3+npv('Yearly Summary'!$B$11, D4:D8)} -> -37235.347 | E9: {=E3+npv('Yearly Summary'!$B$11, E4:E8)} -> 151653.54 | F9: {=F3+npv('Yearly Summary'!$B$11, F4:F8)} -> 455497.97 | G9: {=G3+npv('Yearly Summary'!$B$11, G4:G8)} -> -152190.89 | H9: {=H3+npv('Yearly Summary'!$B$11, H4:H8)} -> 151653.54 | I9: {=I3+npv('Yearly Summary'!$B$11, I4:I8)} -> -416906.55 | J9: {=J3+npv('Yearly Summary'!$B$11, J4:J8)} -> 720213.63
A11: Flat | B11: Variation | C11: 0.5
B13: 𝛥 Capex | E13: 𝛥 Opex | H13: 𝛥 Revenue
A14: Year | B14: Nominal | C14: Low | D14: High | E14: Nominal | F14: Low | G14: High | H14: Nominal | I14: Low | J14: High
A15: 0 | B15: ='Yearly Summary'!B2 -> -100000 | C15: =B15*(1-$C$11) -> -50000 | D15: =B15*(1+$C$11) -> -150000 | E15: ='Yearly Summary'!C2 | H15: ='Yearly Summary'!D2
A16: 1 | B16: ='Yearly Summary'!B3 -> -300000 | C16: =B16*(1-$C$11) -> -150000 | D16: =B16*(1+$C$11) -> -450000 | E16: ='Yearly Summary'!C3 -> -137350 | F16: =E16*(1-$C$11) -> -68675 | G16: =E16*(1+$C$11) -> -206025 | H16: ='Yearly Summary'!D3 -> 233451.77 | I16: =H16*(1-$C$11) -> 116725.89 | J16: =H16*(1+$C$11) -> 350177.66
A17: 2 | B17: ='Yearly Summary'!B4 | E17: ='Yearly Summary'!C4 -> -156683 | F17: =E17*(1-$C$11) -> -78341.5 | G17: =E17*(1+$C$11) -> -235024.5 | H17: ='Yearly Summary'!D4 -> 299951.63 | I17: =H17*(1-$C$11) -> 149975.81 | J17: =H17*(1+$C$11) -> 449927.44
A18: 3 | B18: ='Yearly Summary'!B5 | E18: ='Yearly Summary'!C5 -> -156683 | F18: =E18*(1-$C$11) -> -78341.5 | G18: =E18*(1+$C$11) -> -235024.5 | H18: ='Yearly Summary'!D5 -> 300437.83 | I18: =H18*(1-$C$11) -> 150218.92 | J18: =H18*(1+$C$11) -> 450656.75
A19: 4 | B19: ='Yearly Summary'!B6 | E19: ='Yearly Summary'!C6 -> -156683 | F19: =E19*(1-$C$11) -> -78341.5 | G19: =E19*(1+$C$11) -> -235024.5 | H19: ='Yearly Summary'!D6 -> 300437.83 | I19: =H19*(1-$C$11) -> 150218.92 | J19: =H19*(1+$C$11) -> 450656.75
A20: 5 | B20: ='Yearly Summary'!B7 | E20: ='Yearly Summary'!C7 -> -156683 | F20: =E20*(1-$C$11) -> -78341.5 | G20: =E20*(1+$C$11) -> -235024.5 | H20: ='Yearly Summary'!D7 -> 300437.83 | I20: =H20*(1-$C$11) -> 150218.92 | J20: =H20*(1+$C$11) -> 450656.75

Sheet NPV Proof
A1: Year | B1: Capex | C1: Opex | D1: Revenue | E1: Cash Flow | F1: Discounted CF
A2: 0 | B2: =$C$10*$C$14 -> -100000 | E2: =D2+C2+B2 -> -100000 | F2: =E2/(1+$C$11)^A2 -> -100000
A3: 1 | B3: =3*$C$10*$C$14 -> -300000 | C3: ='Monthly Opex'!N6*$C$14 -> -137350 | D3: ='Monthly Sales'!N7 -> 233451.77 | E3: =D3+C3+B3 -> -203898.23 | F3: =E3/(1+$C$11)^A3 -> -188794.65
A4: 2 | C4: ='Monthly Opex'!N20*$C$14 -> -156683 | D4: ='Monthly Sales'!N20 -> 299951.63 | E4: =D4+C4+B4 -> 143268.63 | F4: =E4/(1+$C$11)^A4 -> 122829.76
A5: 3 | C5: =C4 -> -156683 | D5: ='Monthly Sales'!N29 -> 300437.83 | E5: =D5+C5+B5 -> 143754.83 | F5: =E5/(1+$C$11)^A5 -> 114117.22
A6: 4 | C6: =C5 -> -156683 | D6: =D5 -> 300437.83 | E6: =D6+C6+B6 -> 143754.83 | F6: =E6/(1+$C$11)^A6 -> 105664.09
A7: 5 | C7: =C6 -> -156683 | D7: =D6 -> 300437.83 | E7: =D7+C7+B7 -> 143754.83 | F7: =E7/(1+$C$11)^A7 -> 97837.125
F8: =SUM(F2:F7) -> 151653.54
B9: Assumptions
B10: Capex Per DC | C10: 100000 | E10: NPV (sheet) | F10: {=npv(C11,E2:E7)} -> 140419.95
B11: Discount Rate | C11: 0.08 | E11: IRR | F11: =irr(E2:E7,0.03) -> 0.26477174
B14: Negative costs | C14: -1
B16: Total investment | C16: Total Revenue | D16: ROI
B17: =sum(B2:B3)+sum(C2:C7) -> -1164082 | C17: =sum(D2:D7) -> 1434716.9 | D17: =(C17+B17)/(C14*B17) -> 0.23248783
